ciur/__init__.py
ciur/api2.py
ciur/bnf_parser.py
ciur/cli.py
ciur/dateutil_aditional_languages.py
ciur/decorators.py
ciur/exceptions.py
ciur/helpers.py
ciur/models.py
ciur/optional_requests.py
ciur/py.typed
ciur/rule.py
ciur/shortcuts.py
ciur/xpath_functions.py
ciur/xpath_functions_ciur.py
ciur/parse/__init__.py
ciur/parse/_parse.py
ciur/parse/parse_html.py
ciur/parse/parse_xml.py
ciur/parse/parser_pdf.py
ciur-0.2.3.dist-info/licenses/LICENSE
ciur-0.2.3.dist-info/METADATA
ciur-0.2.3.dist-info/WHEEL
ciur-0.2.3.dist-info/entry_points.txt
ciur-0.2.3.dist-info/top_level.txt
ciur-0.2.3.dist-info/RECORD
