Metadata-Version: 2.4
Name: ciur
Version: 0.2.3
Author-email: Andrei Danciuc <python.ciur@gmail.com>
License-Expression: MIT
Project-URL: Repository, https://github.com/a-da/python-ciur.git
Requires-Python: ==3.13.2
License-File: LICENSE
Requires-Dist: cssselect==1.2.0
Requires-Dist: html5lib==1.1
Requires-Dist: lxml==5.3.1
Requires-Dist: pyparsing==3.2.1
Requires-Dist: python-dateutil==2.9.0.post0
Requires-Dist: requests[security]==2.32.4
Provides-Extra: dev
Requires-Dist: bpython==0.25; extra == "dev"
Requires-Dist: coverage==7.8.2; extra == "dev"
Requires-Dist: isort==6.0.1; extra == "dev"
Requires-Dist: lxml-stubs==0.5.1; extra == "dev"
Requires-Dist: mypy==1.16.0; extra == "dev"
Requires-Dist: pip-audit==2.9.0; extra == "dev"
Requires-Dist: pyenchant==3.2.2; extra == "dev"
Requires-Dist: pylint==3.3.7; extra == "dev"
Requires-Dist: pytest-cov==6.1.1; extra == "dev"
Requires-Dist: pytest-runner==6.0.1; extra == "dev"
Requires-Dist: pytest-sugar==1.0.0; extra == "dev"
Requires-Dist: pytest==8.4.0; extra == "dev"
Requires-Dist: setuptools-lint==0.6.0; extra == "dev"
Requires-Dist: sh==2.2.1; extra == "dev"
Requires-Dist: sphinx==8.2.0; extra == "dev"
Requires-Dist: twine==6.1.0; extra == "dev"
Requires-Dist: types-PyYAML==6.0.12.20250516; extra == "dev"
Requires-Dist: types-html5lib==1.1.11.20241018; extra == "dev"
Requires-Dist: types-python-dateutil==2.9.0.20241206; extra == "dev"
Requires-Dist: types-requests==2.32.0.20250602; extra == "dev"
Requires-Dist: types-retry==0.9.9.20250322; extra == "dev"
Provides-Extra: pdf
Requires-Dist: pdfminer==20191125; extra == "pdf"
Dynamic: license-file
